{
    "fund_name": "ICICI Prudential Credit Risk Fund",
    "fund_house": "ICICI Mutual Fund",
    "fund_category": "Debt",
    "sub_category": "Credit Risk",
    "fund_manager": "Akhil Kakkar, Manish Banthia",
    "nav": "₹37.04",
    "returns_1y": "8.74%",
    "returns_3y": "8.81%",
    "returns_5y": "7.94%",
    "benchmark": "CRISIL Credit Risk Debt TR INR",
    "benchmark_comparison": "1Y: 7.88%, 3Y: 7.48%, 5Y: 8.77%",
    "alpha": "1.00",
    "risk_rating": "Very High Risk",
    "sharpe_ratio": "2.65",
    "expense_ratio": "0.76%",
    "aum": "₹5946 Cr",
    "exit_load": "1.0%",
    "min_investment": "₹100/₹100",
    "lock_in_period": "No Lock-in",
    "source_url": "https://www.indmoney.com/mutual-funds/icici-prudential-credit-risk-fund-direct-plan-growth-378",
    "scraped_at": "2026-04-01T04:52:23.001184"
}